THz_toolkit/__about__.py
THz_toolkit/__init__.py
thz_toolkit-0.0.1.dist-info/METADATA
thz_toolkit-0.0.1.dist-info/WHEEL
thz_toolkit-0.0.1.dist-info/licenses/LICENSE.txt
thz_toolkit-0.0.1.dist-info/RECORD
