Metadata-Version: 2.1
Name: THz-toolkit
Version: 0.0.1
Project-URL: Documentation, https://github.com/unknown/thz-toolkit#readme
Project-URL: Issues, https://github.com/unknown/thz-toolkit/issues
Project-URL: Source, https://github.com/unknown/thz-toolkit
Author-email: jsdodge <jsdodge@sfu.ca>
License-Expression: MIT
License-File: LICENSE.txt
Classifier: Development Status :: 1 - Planning
Classifier: Programming Language :: Python
Classifier: Programming Language :: Python :: 3.7
Classifier: Programming Language :: Python :: 3.8
Classifier: Programming Language :: Python :: 3.9
Classifier: Programming Language :: Python :: 3.10
Classifier: Programming Language :: Python :: 3.11
Classifier: Programming Language :: Python :: Implementation :: CPython
Classifier: Programming Language :: Python :: Implementation :: PyPy
Requires-Python: >=3.7
